[
    {
        "title": "jklkg",
        "details": "kljjjjjjfgggggggg gyuuuuuuuuul",
        "target": 20.5,
        "start_date": "2025-1-12",
        "end_date": "2025-2-12",
        "owner": "kjlo@gmail.com"
    },
    {
        "title": "lkkkk",
        "details": "hfdrukmb",
        "target": 23.0,
        "start_date": "2025-2-12",
        "end_date": "2025-4-12",
        "owner": "kjlo@gmail.com"
    },
    {
        "title": "web",
        "details": "wevlkfklkfkjfjkfdjfdjkjkfjfdjjkfjkdfkfjjd",
        "target": 250.5,
        "start_date": "2025-2-12",
        "end_date": "2025-4-12",
        "owner": "kjlo@gmail.com"
    },
    {
        "title": "logic",
        "details": "lkoig utfkl",
        "target": 639.5,
        "start_date": "2002-6-12",
        "end_date": "2002-12-16",
        "owner": "math@gmail.com"
    }
]